simuq/__init__.py
simuq/_version.py
simuq/config.py
simuq/environment.py
simuq/expression.py
simuq/hamiltonian.py
simuq/provider.py
simuq/qmachine.py
simuq/qsystem.py
simuq/solver.py
simuq/transformation.py
simuq/transpiler.py
simuq/aais/__init__.py
simuq/aais/heisenberg.py
simuq/aais/ibm.py
simuq/aais/ibm_braiding.py
simuq/aais/ionq_arb_2q.py
simuq/aais/ionq_braiding.py
simuq/aais/ising.py
simuq/aais/rigetti.py
simuq/aais/rydberg1d.py
simuq/aais/rydberg1d_global.py
simuq/aais/rydberg2d.py
simuq/aais/rydberg2d_global.py
simuq/aais/two_pauli.py
simuq/backends/__init__.py
simuq/backends/bloqade_rydberg.py
simuq/backends/bloqade_rydberg2d.py
simuq/backends/bloqade_rydberg_aws.py
simuq/backends/ionq_braiding.py
simuq/backends/ionq_circuit.py
simuq/backends/ionq_qiskit_native.py
simuq/backends/ionq_qiskit_native_qaoa.py
simuq/backends/ionq_qiskit_qis.py
simuq/backends/ionq_qiskit_qis_qaoa.py
simuq/backends/ionq_transpiler.py
simuq/backends/ionq_transpiler_2Pauli.py
simuq/backends/qiskit_iontrap.py
simuq/backends/qiskit_zxi_ixz.py
simuq/braket/__init__.py
simuq/braket/braket_ionq_circuit.py
simuq/braket/braket_ionq_transpiler.py
simuq/braket/braket_provider.py
simuq/braket/braket_rydberg_transpiler.py
simuq/dwave/__init__.py
simuq/dwave/dwave_provider.py
simuq/dwave/dwave_transpiler.py
simuq/experimental/__init__.py
simuq/experimental/aais/__init__.py
simuq/experimental/aais/flux_sc.py
simuq/experimental/aais/ibm5.py
simuq/experimental/aais/ibm7.py
simuq/experimental/aais/ibm_27.py
simuq/experimental/aais/ibm_hypothetical.py
simuq/ibm/__init__.py
simuq/ibm/ibm_provider.py
simuq/ibm/qiskit_5.py
simuq/ibm/qiskit_braiding.py
simuq/ibm/qiskit_pulse_ibm.py
simuq/ibm/qiskit_transpiler.py
simuq/ionq/__init__.py
simuq/ionq/ionq_api_circuit.py
simuq/ionq/ionq_api_transpiler.py
simuq/ionq/ionq_provider.py
simuq/qutip/__init__.py
simuq/qutip/qutip_provider.py
simuq/systems/__init__.py
simuq/systems/annealing.py
simuq/systems/bh.py
simuq/systems/floquet.py
simuq/systems/heis5.py
simuq-0.3.1.dist-info/AUTHORS
simuq-0.3.1.dist-info/LICENSE.md
simuq-0.3.1.dist-info/METADATA
simuq-0.3.1.dist-info/WHEEL
simuq-0.3.1.dist-info/top_level.txt
simuq-0.3.1.dist-info/RECORD
