Metadata-Version: 2.1
Name: simuq
Version: 0.3.1
Summary: A Python package for quantum simulation with analog compilation
Home-page: https://pickspeng.github.io/SimuQ/
License: BSD 3-Clause Clear
Classifier: Development Status :: 4 - Beta
Classifier: Intended Audience :: Science/Research
Classifier: Natural Language :: English
Classifier: License :: OSI Approved :: BSD License
Classifier: Programming Language :: Python
Classifier: Programming Language :: Python :: 3.9
Classifier: Programming Language :: Python :: 3.10
Classifier: Programming Language :: Python :: 3.11
License-File: LICENSE.md
License-File: AUTHORS
Requires-Dist: numpy
Requires-Dist: scipy
Requires-Dist: networkx
Provides-Extra: all
Requires-Dist: simuq[braket,dev,ionq,qiskit,qutip] ; extra == 'all'
Provides-Extra: braket
Requires-Dist: matplotlib ; extra == 'braket'
Requires-Dist: amazon-braket-sdk ; extra == 'braket'
Provides-Extra: dev
Requires-Dist: tox ; extra == 'dev'
Provides-Extra: dwave
Requires-Dist: dwave-system ; extra == 'dwave'
Provides-Extra: ionq
Requires-Dist: requests ; extra == 'ionq'
Provides-Extra: qiskit
Requires-Dist: matplotlib ; extra == 'qiskit'
Requires-Dist: qiskit ; extra == 'qiskit'
Requires-Dist: qiskit-ibm-runtime ; extra == 'qiskit'
Requires-Dist: qiskit-aer ; extra == 'qiskit'
Provides-Extra: qutip
Requires-Dist: qutip <5 ; extra == 'qutip'
